{
    "AX": {
        "error": 0.007846703019284588,
        "error_type": "SEM",
        "filter_outliers_dict": {
            "filter_outliers": true,
            "iterations": 1,
            "std_devs": 3,
            "use_iqr_filtering": false,
            "use_standard_deviation_filtering": false
        },
        "fit": "Average",
        "fn": 45,
        "include_baseline_error": true,
        "n": 45,
        "outlier_excluded": [],
        "reviewed": true,
        "user_excluded": [],
        "value": -0.08997454719824924
    },
    "CDD": {
        "error": 3.392604735886885e-06,
        "error_type": "SEM",
        "filter_outliers_dict": {
            "filter_outliers": true,
            "iterations": 1,
            "std_devs": 10,
            "use_iqr_filtering": false,
            "use_standard_deviation_filtering": false
        },
        "fit": "Average",
        "fn": 45,
        "include_baseline_error": true,
        "n": 45,
        "outlier_excluded": [],
        "reviewed": true,
        "user_excluded": [],
        "value": 3.3926047358868853e-06
    },
    "H1": {
        "error": 0.007749063041924046,
        "error_type": "SEM",
        "filter_outliers_dict": {
            "filter_outliers": true,
            "iterations": 1,
            "std_devs": 3,
            "use_iqr_filtering": false,
            "use_standard_deviation_filtering": false
        },
        "fit": "Average",
        "fn": 45,
        "include_baseline_error": true,
        "n": 45,
        "outlier_excluded": [],
        "reviewed": true,
        "user_excluded": [],
        "value": 0.001057595656149917
    },
    "H2": {
        "error": 0.0027675147686940242,
        "error_type": "SEM",
        "filter_outliers_dict": {
            "filter_outliers": true,
            "iterations": 1,
            "std_devs": 2
        },
        "fit": "average",
        "value": -0.040391791451338775
    },
    "L1": {
        "error": 0.004346481404962276,
        "error_type": "SEM",
        "filter_outliers_dict": {
            "filter_outliers": true,
            "iterations": 1,
            "std_devs": 3,
            "use_iqr_filtering": false,
            "use_standard_deviation_filtering": false
        },
        "fit": "Average",
        "fn": 45,
        "include_baseline_error": true,
        "n": 45,
        "outlier_excluded": [],
        "reviewed": true,
        "user_excluded": [],
        "value": 0.017255356691829447
    },
    "L2": {
        "error": 0.008281739261060395,
        "error_type": "SEM",
        "filter_outliers_dict": {
            "filter_outliers": true,
            "iterations": 1,
            "std_devs": 3,
            "use_iqr_filtering": false,
            "use_standard_deviation_filtering": false
        },
        "fit": "Average",
        "fn": 45,
        "include_baseline_error": true,
        "n": 45,
        "outlier_excluded": [],
        "reviewed": true,
        "user_excluded": [],
        "value": -0.06105237183025262
    }
}